{"toysSet":[{"id":3,"name":"Лего","toyType":"Constructor","ageRating":"ThreePlus","material":"Plastic","length":200,"width":200,"height":140,"manufacturer":"ООО \"Легосити\"","cost":2600.0},{"id":2,"name":"Шахматы","toyType":"BoardGame","ageRating":"SevenPlus","material":"Wood","length":400,"width":400,"height":50,"manufacturer":"ООО \"Мудрецов\"","cost":1800.0},{"id":1,"name":"Жигули","toyType":"ToyCar","ageRating":"SevenPlus","material":"Metal","length":120,"width":60,"height":30,"manufacturer":"ЗАО \"Детмаш\"","cost":970.0},{"id":0,"name":"Машенька","toyType":"Doll","ageRating":"ZeroPlus","material":"Plastic","length":40,"width":50,"height":180,"manufacturer":"ООО \"Куклодел\"","cost":1250.0}],"toysQuantity":{"0":14,"1":6,"2":5,"3":19},"toysProcurements":[{"id":0,"toyId":0,"supplier":"ИП \"Импульс\"","quantity":15,"date":"2023-06-14 11:20"},{"id":1,"toyId":1,"supplier":"ИП \"Катанян\"","quantity":8,"date":"2023-06-14 11:20"},{"id":2,"toyId":3,"supplier":"ООО \"Маршал\"","quantity":5,"date":"2023-06-14 11:21"},{"id":3,"toyId":3,"supplier":"ИП \"Воронин\"","quantity":20,"date":"2023-06-14 11:26"}],"toysSales":[{"id":0,"toyId":0,"bayer":"Василий","quantity":1,"date":"2023-06-14 11:28"},{"id":1,"toyId":3,"bayer":"Петр","quantity":1,"date":"2023-06-14 11:29"},{"id":2,"toyId":1,"bayer":"Андрей","quantity":2,"date":"2023-06-14 11:30"}]}